monotonic_derivative/__init__.py
monotonic_derivative/_version.py
monotonic_derivative/curve_smoothing.py
monotonic_derivative/monotonic_derivative.py
monotonic_derivative-0.9.dist-info/LICENSE
monotonic_derivative-0.9.dist-info/METADATA
monotonic_derivative-0.9.dist-info/WHEEL
monotonic_derivative-0.9.dist-info/top_level.txt
monotonic_derivative-0.9.dist-info/RECORD
