Metadata-Version: 2.1
Name: monotonic-derivative
Version: 0.9
Summary: Monotonic Derivative is a Python library designed to modify real-life data to ensure that the specified degree derivative of the cubic spline is always monotonically increasing or decreasing. How ? thanks to it's derivative ! There is also a genetic base curve smoothing tool with several parameter to suit your needs, This library can be particularly useful in applications where the derivatives of the given data must follow specific constraints, such as in scientific modeling/engineering
Home-page: https://github.com/A-Wpro/monotonic_derivative
Author: Adam Wecker
Author-email: adam.wecker0@gmail.com
Classifier: Development Status :: 4 - Beta
Classifier: Intended Audience :: Developers
Classifier: License :: OSI Approved :: MIT License
Classifier: Programming Language :: Python :: 3
Classifier: Programming Language :: Python :: 3.9
Classifier: Programming Language :: Python :: 3.10
License-File: LICENSE
Requires-Dist: numpy
Requires-Dist: scipy
Requires-Dist: matplotlib
Requires-Dist: imageio
